butterrand/__init__.py
butterrand/core.py
butterrand_on-0.0.1.dist-info/licenses/LICENSE
butterrand_on-0.0.1.dist-info/METADATA
butterrand_on-0.0.1.dist-info/WHEEL
butterrand_on-0.0.1.dist-info/top_level.txt
butterrand_on-0.0.1.dist-info/RECORD
