Metadata-Version: 2.4
Name: butterrand-on
Version: 0.0.1
Summary: Random number generator based on butterfly effect and chaotic maps
Home-page: https://github.com/OmeraGod/butterrand-on
Author: Bùi Phong Phú
Author-email: omerasutvailworkit@gmail.com
License: MIT
Classifier: Programming Language :: Python :: 3
Classifier: License :: OSI Approved :: MIT License
Requires-Python: >=3.6
License-File: LICENSE
Dynamic: author
Dynamic: author-email
Dynamic: classifier
Dynamic: description
Dynamic: description-content-type
Dynamic: home-page
Dynamic: license
Dynamic: license-file
Dynamic: requires-python
Dynamic: summary
